<sigml>
                         <hns_sign gloss="1000000">
                            <hamnosys_manual>
                            <hamfinger2/>
<hamthumbacrossmod/>
<hamextfingeru/>
<hampalml/>
<hambetween/>
<hampalmd/>
<hamshoulders/>
<hamlrat/>
<hamparbegin/>
<hamreplace/>
<hamflathand/>
<hamthumbacrossmod/>
<hamindexfinger/>
<hamdoublebent/>
<hamextfingeru/>
<hampalmd/>
<hammover/>
<hamsmallmod/>
<hamarcd/>
<hamsmallmod/>
<hamparend/>
                            </hamnosys_manual>
                        </hns_sign>
                    </sigml>
                    