<sigml>
                         <hns_sign gloss="2_thang">
                            <hamnosys_manual>
                            <hamparbegin/>
<hamfinger23spread/>
<hamthumbacrossmod/>
<hamextfingeruo/>
<hambetween/>
<hamextfingeru/>
<hampalmdl/>
<hamplus/>
<hamflathand/>
<hamthumboutmod/>
<hamextfingeruo/>
<hampalmr/>
<hamparend/>
<hamparbegin/>
<hamthumbball/>
<hamplus/>
<hampalm/>
<hamparend/>
<hamtouch/>
<hamparbegin/>
<hammover/>
<hammoveuo/>
<hamreplace/>
<hamextfingeru/>
<hampalmdl/>
<hamparend/>
                            </hamnosys_manual>
                        </hns_sign>
                    </sigml>
                    