<sigml>
                         <hns_sign gloss="aim">
                            <hamnosys_manual>
                            <hamparbegin/>
<hamflathand/>
<hamthumboutmod/>
<hamplus/>
<hamfinger2/>
<hamthumbacrossmod/>
<hamparend/>
<hamparbegin/>
<hamextfingerol/>
<hambetween/>
<hamextfingerul/>
<hampalml/>
<hamplus/>
<hamextfingeru/>
<hampalmr/>
<hamparend/>
<hammoveur/>
<hamparbegin/>
<hamfingertip/>
<hamthumb/>
<hamplus/>
<hamfingertip/>
<hamindexfinger/>
<hammiddlefinger/>
<hamringfinger/>
<hampinky/>
<hamparend/>
<hamtouch/>
                            </hamnosys_manual>
                        </hns_sign>
                    </sigml>
                    