<sigml>
                         <hns_sign gloss="arrow">
                            <hamnosys_manual>
                            <hamparbegin/>
<hampinch12open/>
<hamplus/>
<hampinch12open/>
<hamparend/>
<hamparbegin/>
<hamextfingeror/>
<hambetween/>
<hamextfingero/>
<hampalml/>
<hamplus/>
<hamextfingeror/>
<hambetween/>
<hamextfingero/>
<hampalmr/>
<hamparend/>
<hamparbegin/>
<hamshoulders/>
<hamlrat/>
<hamplus/>
<hamchest/>
<hamlrat/>
<hamparend/>
<hamparbegin/>
<hammoveil/>
<hamreplace/>
<hamflathand/>
<hamthumbopenmod/>
<hambetween/>
<hamfinger2345/>
<hamparend/>
<hamlrat/>
<hamshoulders/>
<hambetween/>
<hamshoulders/>
                            </hamnosys_manual>
                        </hns_sign>
                    </sigml>
                    