<sigml>
                         <hns_sign gloss="cay_xanh">
                            <hamnosys_manual>
                            <hamparbegin/>
<hamfinger2345/>
<hamthumboutmod/>
<hamextfingeru/>
<hampalmd/>
<hamplus/>
<hamflathand/>
<hamextfingerr/>
<hampalmd/>
<hamparend/>
<hamparbegin/>
<hameyes/>
<hamlrat/>
<hamarmextended/>
<hamplus/>
<hamchest/>
<hambetween/>
<hamshoulders/>
<hamlrbeside/>
<hamparend/>
<hamreplace/>
<hampalmu/>
                            </hamnosys_manual>
                        </hns_sign>
                    </sigml>
                    