<sigml>
                         <hns_sign gloss="chuyên_gia">
                            <hamnosys_manual>
                            <hamfinger2345/>
<hamthumboutmod/>
<hambetween/>
<hamfist/>
<hamthumboutmod/>
<hamextfingeru/>
<hampalml/>
<hamforehead/>
<hamclose/>
<hamreplace/>
<hamfinger2345/>
<hamthumbacrossmod/>
<hambetween/>
<hamfist/>
<hamthumbacrossmod/>
<hamreplace/>
<hamfinger2345/>
<hamthumboutmod/>
<hambetween/>
<hamfist/>
<hamthumboutmod/>
<hamrepeatfromstart/>
                            </hamnosys_manual>
                        </hns_sign>
                    </sigml>
                    