<sigml>
                         <hns_sign gloss="dong_ho">
                            <hamnosys_manual>
                            <hamparbegin/>
<hampinchall/>
<hamfingerstraightmod/>
<hambetween/>
<hampinchall/>
<hamextfingerol/>
<hampalmd/>
<hamplus/>
<hamfist/>
<hamextfingeror/>
<hampalmd/>
<hamparend/>
<hamparbegin/>
<hamwristback/>
<hamplus/>
<hammiddlefinger/>
<hamfingertip/>
<hamtouch/>
<hamparend/>
                            </hamnosys_manual>
                        </hns_sign>
                    </sigml>
                    