<sigml>
                         <hns_sign gloss="enjoy">
                            <hamnosys_manual>
                            <hamparbegin/>
<hamflathand/>
<hamthumboutmod/>
<hamplus/>
<hamflathand/>
<hamthumboutmod/>
<hamparend/>
<hamparbegin/>
<hamextfingeruo/>
<hampalml/>
<hamplus/>
<hamextfingero/>
<hampalmur/>
<hamparend/>
<hamparbegin/>
<hamshoulders/>
<hamlrat/>
<hamplus/>
<hamstomach/>
<hambetween/>
<hamchest/>
<hamparend/>
<hamparbegin/>
<hammovel/>
<hamlargemod/>
<hamarcd/>
<hamreplace/>
<hamextfingerul/>
<hampalmd/>
<hamparend/>
<hamrepeatfromstart/>
                            </hamnosys_manual>
                        </hns_sign>
                    </sigml>
                    