<sigml>
                         <hns_sign gloss="hoat_dong">
                            <hamnosys_manual>
                            <hamsymmlr/>
<hamfist/>
<hamthumboutmod/>
<hamparbegin/>
<hamextfingerl/>
<hampalml/>
<hamplus/>
<hamextfingerr/>
<hampalmr/>
<hamparend/>
<hamparbegin/>
<hamshoulders/>
<hamplus/>
<hamchest/>
<hamparend/>
<hamparbegin/>
<hammovei/>
<hamparbegin/>
<hammoved/>
<hamcircler/>
<hammoveu/>
<hammoveo/>
<hamparend/>
<hamplus/>
<hamparbegin/>
<hammoveu/>
<hammoveu/>
<hamcircler/>
<hammoved/>
<hammovei/>
<hamparend/>
<hammoved/>
<hammoveo/>
<hamparend/>
<hamrepeatfromstart/>
                            </hamnosys_manual>
                        </hns_sign>
                    </sigml>
                    