<sigml>
                         <hns_sign gloss="met">
                            <hamnosys_manual>
                            <hamfinger2345/>
<hamthumboutmod/>
<hamextfingerdi/>
<hambetween/>
<hamextfingerl/>
<hampalmur/>
<hamstomach/>
<hamlrat/>
<hamclose/>
<hamparbegin/>
<hammoveu/>
<hamlargemod/>
<hamarcl/>
<hamreplace/>
<hamextfingerul/>
<hampalmdl/>
<hamparend/>
<hamrepeatfromstart/>
                            </hamnosys_manual>
                        </hns_sign>
                    </sigml>
                    