<sigml>
                         <hns_sign gloss="monkey">
                            <hamnosys_manual>
                            <hamsymmlr/>
<hamfinger2345/>
<hamthumbopenmod/>
<hamfingerbendmod/>
<hambetween/>
<hamfinger2345/>
<hamthumboutmod/>
<hamextfingerl/>
<hambetween/>
<hamextfingerdl/>
<hampalmdl/>
<hambetween/>
<hampalmu/>
<hamshoulders/>
<hamlrbeside/>
<hambetween/>
<hamchest/>
<hamlrat/>
<hamclose/>
<hamnodding/>
                            </hamnosys_manual>
                        </hns_sign>
                    </sigml>
                    