<sigml>
                         <hns_sign gloss="museum">
                            <hamnosys_manual>
                            <hamsymmlr/>
<hamflathand/>
<hamthumboutmod/>
<hamextfingeru/>
<hampalmu/>
<hamparbegin/>
<hampinkyside/>
<hamplus/>
<hampinkyside/>
<hamparend/>
<hamtouch/>
<hamshoulders/>
<hamparbegin/>
<hammover/>
<hamslow/>
<hamreplace/>
<hamextfingeru/>
<hampalml/>
<hambetween/>
<hampalmul/>
<hamparend/>
<hammovei/>
                            </hamnosys_manual>
                        </hns_sign>
                    </sigml>
                    