<sigml>
                         <hns_sign gloss="mặt_trăng">
                            <hamnosys_manual>
                            <hampinch12/>
<hamfingerstraightmod/>
<hambetween/>
<hampinch12/>
<hamextfingero/>
<hampalmul/>
<hamparbegin/>
<hammoveu/>
<hamlargemod/>
<hammoveu/>
<hammoveo/>
<hammover/>
<hamparend/>
<hamreplace/>
<hamfinger2/>
<hamthumbopenmod/>
<hambetween/>
<hamfinger2/>
<hamthumbopenmod/>
<hamindexfinger/>
<hamfingerbendmod/>
<hamparbegin/>
<hamreplace/>
<hampinch12/>
<hamfingerstraightmod/>
<hambetween/>
<hampinch12/>
<hamextfingero/>
<hampalmd/>
<hammoved/>
<hammoved/>
<hamarcl/>
<hamparend/>
<hamparbegin/>
<hamreplace/>
<hamfinger2/>
<hamthumbacrossmod/>
<hamextfingeru/>
<hampalmd/>
<hamhead/>
<hamlrat/>
<hammoveu/>
<hamsmallmod/>
<hammoveu/>
<hamsmallmod/>
<hamparend/>
                            </hamnosys_manual>
                        </hns_sign>
                    </sigml>
                    