<sigml>
                         <hns_sign gloss="phim">
                            <hamnosys_manual>
                            <hamparbegin/>
<hamfist/>
<hamextfingeru/>
<hampalmd/>
<hamplus/>
<hamceeall/>
<hamthumbopenmod/>
<hamextfingerui/>
<hampalmr/>
<hamparend/>
<hamparbegin/>
<hamear/>
<hamlrbeside/>
<hamplus/>
<hameyes/>
<hamparend/>
<hamcirclel/>
<hamrepeatfromstart/>
                            </hamnosys_manual>
                        </hns_sign>
                    </sigml>
                    