<sigml>
                         <hns_sign gloss="đám_cưới">
                            <hamnosys_manual>
                            <hamsymmpar/>
<hamflathand/>
<hamthumboutmod/>
<hamparbegin/>
<hamextfingerl/>
<hambetween/>
<hamextfingerul/>
<hampalmu/>
<hamplus/>
<hamextfingeruo/>
<hampalmu/>
<hamparend/>
<hamseqbegin/>
<hamtouch/>
<hamwristback/>
<hamseqend/>
<hamparbegin/>
<hamparbegin/>
<hammoveu/>
<hammovei/>
<hamsmallmod/>
<hamparend/>
<hamplus/>
<hammoveu/>
<hamparend/>
<hamparbegin/>
<hamparbegin/>
<hammover/>
<hamlargemod/>
<hammoved/>
<hamsmallmod/>
<hammoved/>
<hamsmallmod/>
<hamparend/>
<hamplus/>
<hammovel/>
<hamparend/>
                            </hamnosys_manual>
                        </hns_sign>
                    </sigml>
                    